djangoldp_subscription/__init__.py
djangoldp_subscription/admin.py
djangoldp_subscription/apps.py
djangoldp_subscription/models.py
djangoldp_subscription/tests.py
djangoldp_subscription/migrations/0001_initial.py
djangoldp_subscription/migrations/0002_auto_20200824_2342.py
djangoldp_subscription/migrations/0003_auto_20200825_0009.py
djangoldp_subscription/migrations/0004_auto_20200825_0013.py
djangoldp_subscription/migrations/0005_auto_20200826_1137.py
djangoldp_subscription/migrations/0006_auto_20200827_1157.py
djangoldp_subscription/migrations/0007_auto_20200922_1128.py
djangoldp_subscription/migrations/0008_member_servicesattestation.py
djangoldp_subscription/migrations/0009_auto_20201008_1542.py
djangoldp_subscription/migrations/0010_auto_20201124_1553.py
djangoldp_subscription/migrations/0011_member_subscriptiondate.py
djangoldp_subscription/migrations/0012_auto_20201124_1712.py
djangoldp_subscription/migrations/__init__.py
djangoldp_subscription/templates/__init__.py
djangoldp_subscription/templates/souscripteur_email.txt
djangoldp_subscription-1.0.6.dist-info/METADATA
djangoldp_subscription-1.0.6.dist-info/WHEEL
djangoldp_subscription-1.0.6.dist-info/top_level.txt
djangoldp_subscription-1.0.6.dist-info/RECORD
